pyplottr/__init__.py
pyplottr/pyplottr.py
pyplottr-0.2.4.dist-info/LICENSE
pyplottr-0.2.4.dist-info/METADATA
pyplottr-0.2.4.dist-info/WHEEL
pyplottr-0.2.4.dist-info/top_level.txt
pyplottr-0.2.4.dist-info/zip-safe
pyplottr-0.2.4.dist-info/RECORD
