Metadata-Version: 2.1
Name: pyplottr
Version: 0.2.4
Summary: Matplotlib for humans
Home-page: http://github.com/toaarnio/pyplottr
Author: Tomi Aarnio
Author-email: tomi.p.aarnio@gmail.com
License: Apache License 2.0
Platform: UNKNOWN
Requires-Dist: matplotlib (>=3.1.1)
Requires-Dist: numpy (>=1.17.2)
